[{"Date":"Sep 17, 2019","Open":"$0.09052","High":"$0.1003","Low":"$0.08005","Close":"$0.08692","Volume":"$14,772,274","MarketCap":"$0"},{"Date":"Sep 17, 2019","Open":"$0.09052","High":"$0.1003","Low":"$0.08005","Close":"$0.08692","Volume":"$14,772,274","MarketCap":"$0"},{"Date":"Sep 17, 2019","Open":"$0.09052","High":"$0.1003","Low":"$0.08005","Close":"$0.08692","Volume":"$14,772,274","MarketCap":"$0"},{"Date":"Sep 17, 2019","Open":"$0.09052","High":"$0.1003","Low":"$0.08005","Close":"$0.08692","Volume":"$14,772,274","MarketCap":"$0"},{"Date":"Sep 17, 2019","Open":"$0.09052","High":"$0.1003","Low":"$0.08005","Close":"$0.08692","Volume":"$14,772,274","MarketCap":"$0"},{"Date":"Sep 17, 2019","Open":"$0.09052","High":"$0.1003","Low":"$0.08005","Close":"$0.08692","Volume":"$14,772,274","MarketCap":"$0"},{"Date":"Sep 17, 2019","Open":"$0.09052","High":"$0.1003","Low":"$0.08005","Close":"$0.08692","Volume":"$14,772,274","MarketCap":"$0"},{"Date":"Sep 17, 2019","Open":"$0.09052","High":"$0.1003","Low":"$0.08005","Close":"$0.08692","Volume":"$14,772,274","MarketCap":"$0"},{"Date":"Sep 17, 2019","Open":"$0.09052","High":"$0.1003","Low":"$0.08005","Close":"$0.08692","Volume":"$14,772,274","MarketCap":"$0"},{"Date":"Sep 17, 2019","Open":"$0.09052","High":"$0.1003","Low":"$0.08005","Close":"$0.08692","Volume":"$14,772,274","MarketCap":"$0"},{"Date":"Sep 17, 2019","Open":"$0.09052","High":"$0.1003","Low":"$0.08005","Close":"$0.08692","Volume":"$14,772,274","MarketCap":"$0"},{"Date":"Sep 17, 2019","Open":"$0.09052","High":"$0.1003","Low":"$0.08005","Close":"$0.08692","Volume":"$14,772,274","MarketCap":"$0"},{"Date":"Sep 17, 2019","Open":"$0.09052","High":"$0.1003","Low":"$0.08005","Close":"$0.08692","Volume":"$14,772,274","MarketCap":"$0"},{"Date":"Sep 17, 2019","Open":"$0.09052","High":"$0.1003","Low":"$0.08005","Close":"$0.08692","Volume":"$14,772,274","MarketCap":"$0"},{"Date":"Sep 17, 2019","Open":"$0.09052","High":"$0.1003","Low":"$0.08005","Close":"$0.08692","Volume":"$14,772,274","MarketCap":"$0"},{"Date":"Sep 17, 2019","Open":"$0.09052","High":"$0.1003","Low":"$0.08005","Close":"$0.08692","Volume":"$14,772,274","MarketCap":"$0"},{"Date":"Sep 17, 2019","Open":"$0.09052","High":"$0.1003","Low":"$0.08005","Close":"$0.08692","Volume":"$14,772,274","MarketCap":"$0"},{"Date":"Sep 17, 2019","Open":"$0.09052","High":"$0.1003","Low":"$0.08005","Close":"$0.08692","Volume":"$14,772,274","MarketCap":"$0"},{"Date":"Sep 17, 2019","Open":"$0.09052","High":"$0.1003","Low":"$0.08005","Close":"$0.08692","Volume":"$14,772,274","MarketCap":"$0"},{"Date":"Sep 17, 2019","Open":"$0.09052","High":"$0.1003","Low":"$0.08005","Close":"$0.08692","Volume":"$14,772,274","MarketCap":"$0"},{"Date":"Sep 17, 2019","Open":"$0.09052","High":"$0.1003","Low":"$0.08005","Close":"$0.08692","Volume":"$14,772,274","MarketCap":"$0"},{"Date":"Sep 17, 2019","Open":"$0.09052","High":"$0.1003","Low":"$0.08005","Close":"$0.08692","Volume":"$14,772,274","MarketCap":"$0"},{"Date":"Sep 17, 2019","Open":"$0.09052","High":"$0.1003","Low":"$0.08005","Close":"$0.08692","Volume":"$14,772,274","MarketCap":"$0"},{"Date":"Sep 17, 2019","Open":"$0.09052","High":"$0.1003","Low":"$0.08005","Close":"$0.08692","Volume":"$14,772,274","MarketCap":"$0"},{"Date":"Sep 17, 2019","Open":"$0.09052","High":"$0.1003","Low":"$0.08005","Close":"$0.08692","Volume":"$14,772,274","MarketCap":"$0"},{"Date":"Sep 17, 2019","Open":"$0.09052","High":"$0.1003","Low":"$0.08005","Close":"$0.08692","Volume":"$14,772,274","MarketCap":"$0"},{"Date":"Sep 17, 2019","Open":"$0.09052","High":"$0.1003","Low":"$0.08005","Close":"$0.08692","Volume":"$14,772,274","MarketCap":"$0"},{"Date":"Sep 17, 2019","Open":"$0.09052","High":"$0.1003","Low":"$0.08005","Close":"$0.08692","Volume":"$14,772,274","MarketCap":"$0"},{"Date":"Sep 17, 2019","Open":"$0.09052","High":"$0.1003","Low":"$0.08005","Close":"$0.08692","Volume":"$14,772,274","MarketCap":"$0"},{"Date":"Sep 17, 2019","Open":"$0.09052","High":"$0.1003","Low":"$0.08005","Close":"$0.08692","Volume":"$14,772,274","MarketCap":"$0"},{"Date":"Sep 17, 2019","Open":"$0.09052","High":"$0.1003","Low":"$0.08005","Close":"$0.08692","Volume":"$14,772,274","MarketCap":"$0"},{"Date":"Sep 17, 2019","Open":"$0.09052","High":"$0.1003","Low":"$0.08005","Close":"$0.08692","Volume":"$14,772,274","MarketCap":"$0"},{"Date":"Sep 17, 2019","Open":"$0.09052","High":"$0.1003","Low":"$0.08005","Close":"$0.08692","Volume":"$14,772,274","MarketCap":"$0"},{"Date":"Sep 17, 2019","Open":"$0.09052","High":"$0.1003","Low":"$0.08005","Close":"$0.08692","Volume":"$14,772,274","MarketCap":"$0"},{"Date":"Sep 17, 2019","Open":"$0.09052","High":"$0.1003","Low":"$0.08005","Close":"$0.08692","Volume":"$14,772,274","MarketCap":"$0"},{"Date":"Sep 17, 2019","Open":"$0.09052","High":"$0.1003","Low":"$0.08005","Close":"$0.08692","Volume":"$14,772,274","MarketCap":"$0"},{"Date":"Sep 17, 2019","Open":"$0.09052","High":"$0.1003","Low":"$0.08005","Close":"$0.08692","Volume":"$14,772,274","MarketCap":"$0"},{"Date":"Sep 17, 2019","Open":"$0.09052","High":"$0.1003","Low":"$0.08005","Close":"$0.08692","Volume":"$14,772,274","MarketCap":"$0"},{"Date":"Sep 17, 2019","Open":"$0.09052","High":"$0.1003","Low":"$0.08005","Close":"$0.08692","Volume":"$14,772,274","MarketCap":"$0"},{"Date":"Sep 17, 2019","Open":"$0.09052","High":"$0.1003","Low":"$0.08005","Close":"$0.08692","Volume":"$14,772,274","MarketCap":"$0"},{"Date":"Sep 17, 2019","Open":"$0.09052","High":"$0.1003","Low":"$0.08005","Close":"$0.08692","Volume":"$14,772,274","MarketCap":"$0"},{"Date":"Sep 17, 2019","Open":"$0.09052","High":"$0.1003","Low":"$0.08005","Close":"$0.08692","Volume":"$14,772,274","MarketCap":"$0"},{"Date":"Sep 17, 2019","Open":"$0.09052","High":"$0.1003","Low":"$0.08005","Close":"$0.08692","Volume":"$14,772,274","MarketCap":"$0"},{"Date":"Sep 17, 2019","Open":"$0.09052","High":"$0.1003","Low":"$0.08005","Close":"$0.08692","Volume":"$14,772,274","MarketCap":"$0"},{"Date":"Sep 17, 2019","Open":"$0.09052","High":"$0.1003","Low":"$0.08005","Close":"$0.08692","Volume":"$14,772,274","MarketCap":"$0"},{"Date":"Sep 17, 2019","Open":"$0.09052","High":"$0.1003","Low":"$0.08005","Close":"$0.08692","Volume":"$14,772,274","MarketCap":"$0"},{"Date":"Sep 17, 2019","Open":"$0.09052","High":"$0.1003","Low":"$0.08005","Close":"$0.08692","Volume":"$14,772,274","MarketCap":"$0"},{"Date":"Sep 17, 2019","Open":"$0.09052","High":"$0.1003","Low":"$0.08005","Close":"$0.08692","Volume":"$14,772,274","MarketCap":"$0"},{"Date":"Sep 17, 2019","Open":"$0.09052","High":"$0.1003","Low":"$0.08005","Close":"$0.08692","Volume":"$14,772,274","MarketCap":"$0"},{"Date":"Sep 17, 2019","Open":"$0.09052","High":"$0.1003","Low":"$0.08005","Close":"$0.08692","Volume":"$14,772,274","MarketCap":"$0"},{"Date":"Sep 17, 2019","Open":"$0.09052","High":"$0.1003","Low":"$0.08005","Close":"$0.08692","Volume":"$14,772,274","MarketCap":"$0"},{"Date":"Sep 17, 2019","Open":"$0.09052","High":"$0.1003","Low":"$0.08005","Close":"$0.08692","Volume":"$14,772,274","MarketCap":"$0"},{"Date":"Sep 17, 2019","Open":"$0.09052","High":"$0.1003","Low":"$0.08005","Close":"$0.08692","Volume":"$14,772,274","MarketCap":"$0"},{"Date":"Sep 17, 2019","Open":"$0.09052","High":"$0.1003","Low":"$0.08005","Close":"$0.08692","Volume":"$14,772,274","MarketCap":"$0"},{"Date":"Sep 17, 2019","Open":"$0.09052","High":"$0.1003","Low":"$0.08005","Close":"$0.08692","Volume":"$14,772,274","MarketCap":"$0"},{"Date":"Sep 17, 2019","Open":"$0.09052","High":"$0.1003","Low":"$0.08005","Close":"$0.08692","Volume":"$14,772,274","MarketCap":"$0"},{"Date":"Sep 17, 2019","Open":"$0.09052","High":"$0.1003","Low":"$0.08005","Close":"$0.08692","Volume":"$14,772,274","MarketCap":"$0"},{"Date":"Sep 17, 2019","Open":"$0.09052","High":"$0.1003","Low":"$0.08005","Close":"$0.08692","Volume":"$14,772,274","MarketCap":"$0"},{"Date":"Sep 17, 2019","Open":"$0.09052","High":"$0.1003","Low":"$0.08005","Close":"$0.08692","Volume":"$14,772,274","MarketCap":"$0"},{"Date":"Sep 17, 2019","Open":"$0.09052","High":"$0.1003","Low":"$0.08005","Close":"$0.08692","Volume":"$14,772,274","MarketCap":"$0"},{"Date":"Sep 17, 2019","Open":"$0.09052","High":"$0.1003","Low":"$0.08005","Close":"$0.08692","Volume":"$14,772,274","MarketCap":"$0"},{"Date":"Sep 17, 2019","Open":"$0.09052","High":"$0.1003","Low":"$0.08005","Close":"$0.08692","Volume":"$14,772,274","MarketCap":"$0"},{"Date":"Sep 17, 2019","Open":"$0.09052","High":"$0.1003","Low":"$0.08005","Close":"$0.08692","Volume":"$14,772,274","MarketCap":"$0"},{"Date":"Sep 17, 2019","Open":"$0.09052","High":"$0.1003","Low":"$0.08005","Close":"$0.08692","Volume":"$14,772,274","MarketCap":"$0"},{"Date":"Sep 17, 2019","Open":"$0.09052","High":"$0.1003","Low":"$0.08005","Close":"$0.08692","Volume":"$14,772,274","MarketCap":"$0"},{"Date":"Sep 17, 2019","Open":"$0.09052","High":"$0.1003","Low":"$0.08005","Close":"$0.08692","Volume":"$14,772,274","MarketCap":"$0"},{"Date":"Sep 17, 2019","Open":"$0.09052","High":"$0.1003","Low":"$0.08005","Close":"$0.08692","Volume":"$14,772,274","MarketCap":"$0"},{"Date":"Sep 17, 2019","Open":"$0.09052","High":"$0.1003","Low":"$0.08005","Close":"$0.08692","Volume":"$14,772,274","MarketCap":"$0"},{"Date":"Sep 17, 2019","Open":"$0.09052","High":"$0.1003","Low":"$0.08005","Close":"$0.08692","Volume":"$14,772,274","MarketCap":"$0"},{"Date":"Sep 17, 2019","Open":"$0.09052","High":"$0.1003","Low":"$0.08005","Close":"$0.08692","Volume":"$14,772,274","MarketCap":"$0"},{"Date":"Sep 17, 2019","Open":"$0.09052","High":"$0.1003","Low":"$0.08005","Close":"$0.08692","Volume":"$14,772,274","MarketCap":"$0"},{"Date":"Sep 17, 2019","Open":"$0.09052","High":"$0.1003","Low":"$0.08005","Close":"$0.08692","Volume":"$14,772,274","MarketCap":"$0"},{"Date":"Sep 17, 2019","Open":"$0.09052","High":"$0.1003","Low":"$0.08005","Close":"$0.08692","Volume":"$14,772,274","MarketCap":"$0"},{"Date":"Sep 17, 2019","Open":"$0.09052","High":"$0.1003","Low":"$0.08005","Close":"$0.08692","Volume":"$14,772,274","MarketCap":"$0"},{"Date":"Sep 17, 2019","Open":"$0.09052","High":"$0.1003","Low":"$0.08005","Close":"$0.08692","Volume":"$14,772,274","MarketCap":"$0"},{"Date":"Sep 17, 2019","Open":"$0.09052","High":"$0.1003","Low":"$0.08005","Close":"$0.08692","Volume":"$14,772,274","MarketCap":"$0"},{"Date":"Sep 17, 2019","Open":"$0.09052","High":"$0.1003","Low":"$0.08005","Close":"$0.08692","Volume":"$14,772,274","MarketCap":"$0"},{"Date":"Sep 17, 2019","Open":"$0.09052","High":"$0.1003","Low":"$0.08005","Close":"$0.08692","Volume":"$14,772,274","MarketCap":"$0"},{"Date":"Sep 17, 2019","Open":"$0.09052","High":"$0.1003","Low":"$0.08005","Close":"$0.08692","Volume":"$14,772,274","MarketCap":"$0"},{"Date":"Sep 17, 2019","Open":"$0.09052","High":"$0.1003","Low":"$0.08005","Close":"$0.08692","Volume":"$14,772,274","MarketCap":"$0"},{"Date":"Sep 17, 2019","Open":"$0.09052","High":"$0.1003","Low":"$0.08005","Close":"$0.08692","Volume":"$14,772,274","MarketCap":"$0"},{"Date":"Sep 17, 2019","Open":"$0.09052","High":"$0.1003","Low":"$0.08005","Close":"$0.08692","Volume":"$14,772,274","MarketCap":"$0"},{"Date":"Sep 17, 2019","Open":"$0.09052","High":"$0.1003","Low":"$0.08005","Close":"$0.08692","Volume":"$14,772,274","MarketCap":"$0"},{"Date":"Sep 17, 2019","Open":"$0.09052","High":"$0.1003","Low":"$0.08005","Close":"$0.08692","Volume":"$14,772,274","MarketCap":"$0"},{"Date":"Sep 17, 2019","Open":"$0.09052","High":"$0.1003","Low":"$0.08005","Close":"$0.08692","Volume":"$14,772,274","MarketCap":"$0"},{"Date":"Sep 17, 2019","Open":"$0.09052","High":"$0.1003","Low":"$0.08005","Close":"$0.08692","Volume":"$14,772,274","MarketCap":"$0"},{"Date":"Sep 17, 2019","Open":"$0.09052","High":"$0.1003","Low":"$0.08005","Close":"$0.08692","Volume":"$14,772,274","MarketCap":"$0"},{"Date":"Sep 17, 2019","Open":"$0.09052","High":"$0.1003","Low":"$0.08005","Close":"$0.08692","Volume":"$14,772,274","MarketCap":"$0"},{"Date":"Sep 17, 2019","Open":"$0.09052","High":"$0.1003","Low":"$0.08005","Close":"$0.08692","Volume":"$14,772,274","MarketCap":"$0"},{"Date":"Sep 17, 2019","Open":"$0.09052","High":"$0.1003","Low":"$0.08005","Close":"$0.08692","Volume":"$14,772,274","MarketCap":"$0"},{"Date":"Sep 17, 2019","Open":"$0.09052","High":"$0.1003","Low":"$0.08005","Close":"$0.08692","Volume":"$14,772,274","MarketCap":"$0"},{"Date":"Sep 17, 2019","Open":"$0.09052","High":"$0.1003","Low":"$0.08005","Close":"$0.08692","Volume":"$14,772,274","MarketCap":"$0"},{"Date":"Sep 17, 2019","Open":"$0.09052","High":"$0.1003","Low":"$0.08005","Close":"$0.08692","Volume":"$14,772,274","MarketCap":"$0"},{"Date":"Sep 17, 2019","Open":"$0.09052","High":"$0.1003","Low":"$0.08005","Close":"$0.08692","Volume":"$14,772,274","MarketCap":"$0"},{"Date":"Sep 17, 2019","Open":"$0.09052","High":"$0.1003","Low":"$0.08005","Close":"$0.08692","Volume":"$14,772,274","MarketCap":"$0"},{"Date":"Sep 17, 2019","Open":"$0.09052","High":"$0.1003","Low":"$0.08005","Close":"$0.08692","Volume":"$14,772,274","MarketCap":"$0"},{"Date":"Sep 17, 2019","Open":"$0.09052","High":"$0.1003","Low":"$0.08005","Close":"$0.08692","Volume":"$14,772,274","MarketCap":"$0"},{"Date":"Sep 17, 2019","Open":"$0.09052","High":"$0.1003","Low":"$0.08005","Close":"$0.08692","Volume":"$14,772,274","MarketCap":"$0"},{"Date":"Sep 17, 2019","Open":"$0.09052","High":"$0.1003","Low":"$0.08005","Close":"$0.08692","Volume":"$14,772,274","MarketCap":"$0"},{"Date":"Sep 17, 2019","Open":"$0.09052","High":"$0.1003","Low":"$0.08005","Close":"$0.08692","Volume":"$14,772,274","MarketCap":"$0"},{"Date":"Sep 17, 2019","Open":"$0.09052","High":"$0.1003","Low":"$0.08005","Close":"$0.08692","Volume":"$14,772,274","MarketCap":"$0"},{"Date":"Sep 17, 2019","Open":"$0.09052","High":"$0.1003","Low":"$0.08005","Close":"$0.08692","Volume":"$14,772,274","MarketCap":"$0"},{"Date":"Sep 17, 2019","Open":"$0.09052","High":"$0.1003","Low":"$0.08005","Close":"$0.08692","Volume":"$14,772,274","MarketCap":"$0"},{"Date":"Sep 17, 2019","Open":"$0.09052","High":"$0.1003","Low":"$0.08005","Close":"$0.08692","Volume":"$14,772,274","MarketCap":"$0"},{"Date":"Sep 17, 2019","Open":"$0.09052","High":"$0.1003","Low":"$0.08005","Close":"$0.08692","Volume":"$14,772,274","MarketCap":"$0"},{"Date":"Sep 17, 2019","Open":"$0.09052","High":"$0.1003","Low":"$0.08005","Close":"$0.08692","Volume":"$14,772,274","MarketCap":"$0"},{"Date":"Sep 17, 2019","Open":"$0.09052","High":"$0.1003","Low":"$0.08005","Close":"$0.08692","Volume":"$14,772,274","MarketCap":"$0"},{"Date":"Sep 17, 2019","Open":"$0.09052","High":"$0.1003","Low":"$0.08005","Close":"$0.08692","Volume":"$14,772,274","MarketCap":"$0"},{"Date":"Sep 17, 2019","Open":"$0.09052","High":"$0.1003","Low":"$0.08005","Close":"$0.08692","Volume":"$14,772,274","MarketCap":"$0"},{"Date":"Sep 17, 2019","Open":"$0.09052","High":"$0.1003","Low":"$0.08005","Close":"$0.08692","Volume":"$14,772,274","MarketCap":"$0"},{"Date":"Sep 17, 2019","Open":"$0.09052","High":"$0.1003","Low":"$0.08005","Close":"$0.08692","Volume":"$14,772,274","MarketCap":"$0"},{"Date":"Sep 17, 2019","Open":"$0.09052","High":"$0.1003","Low":"$0.08005","Close":"$0.08692","Volume":"$14,772,274","MarketCap":"$0"},{"Date":"Sep 17, 2019","Open":"$0.09052","High":"$0.1003","Low":"$0.08005","Close":"$0.08692","Volume":"$14,772,274","MarketCap":"$0"},{"Date":"Sep 17, 2019","Open":"$0.09052","High":"$0.1003","Low":"$0.08005","Close":"$0.08692","Volume":"$14,772,274","MarketCap":"$0"},{"Date":"Sep 17, 2019","Open":"$0.09052","High":"$0.1003","Low":"$0.08005","Close":"$0.08692","Volume":"$14,772,274","MarketCap":"$0"},{"Date":"Sep 17, 2019","Open":"$0.09052","High":"$0.1003","Low":"$0.08005","Close":"$0.08692","Volume":"$14,772,274","MarketCap":"$0"},{"Date":"Sep 17, 2019","Open":"$0.09052","High":"$0.1003","Low":"$0.08005","Close":"$0.08692","Volume":"$14,772,274","MarketCap":"$0"},{"Date":"Sep 17, 2019","Open":"$0.09052","High":"$0.1003","Low":"$0.08005","Close":"$0.08692","Volume":"$14,772,274","MarketCap":"$0"},{"Date":"Sep 17, 2019","Open":"$0.09052","High":"$0.1003","Low":"$0.08005","Close":"$0.08692","Volume":"$14,772,274","MarketCap":"$0"},{"Date":"Sep 17, 2019","Open":"$0.09052","High":"$0.1003","Low":"$0.08005","Close":"$0.08692","Volume":"$14,772,274","MarketCap":"$0"},{"Date":"Sep 17, 2019","Open":"$0.09052","High":"$0.1003","Low":"$0.08005","Close":"$0.08692","Volume":"$14,772,274","MarketCap":"$0"},{"Date":"Sep 17, 2019","Open":"$0.09052","High":"$0.1003","Low":"$0.08005","Close":"$0.08692","Volume":"$14,772,274","MarketCap":"$0"},{"Date":"Sep 17, 2019","Open":"$0.09052","High":"$0.1003","Low":"$0.08005","Close":"$0.08692","Volume":"$14,772,274","MarketCap":"$0"},{"Date":"Sep 17, 2019","Open":"$0.09052","High":"$0.1003","Low":"$0.08005","Close":"$0.08692","Volume":"$14,772,274","MarketCap":"$0"},{"Date":"Sep 17, 2019","Open":"$0.09052","High":"$0.1003","Low":"$0.08005","Close":"$0.08692","Volume":"$14,772,274","MarketCap":"$0"},{"Date":"Sep 17, 2019","Open":"$0.09052","High":"$0.1003","Low":"$0.08005","Close":"$0.08692","Volume":"$14,772,274","MarketCap":"$0"},{"Date":"Sep 17, 2019","Open":"$0.09052","High":"$0.1003","Low":"$0.08005","Close":"$0.08692","Volume":"$14,772,274","MarketCap":"$0"},{"Date":"Sep 17, 2019","Open":"$0.09052","High":"$0.1003","Low":"$0.08005","Close":"$0.08692","Volume":"$14,772,274","MarketCap":"$0"},{"Date":"Sep 17, 2019","Open":"$0.09052","High":"$0.1003","Low":"$0.08005","Close":"$0.08692","Volume":"$14,772,274","MarketCap":"$0"},{"Date":"Sep 17, 2019","Open":"$0.09052","High":"$0.1003","Low":"$0.08005","Close":"$0.08692","Volume":"$14,772,274","MarketCap":"$0"},{"Date":"Sep 17, 2019","Open":"$0.09052","High":"$0.1003","Low":"$0.08005","Close":"$0.08692","Volume":"$14,772,274","MarketCap":"$0"},{"Date":"Sep 17, 2019","Open":"$0.09052","High":"$0.1003","Low":"$0.08005","Close":"$0.08692","Volume":"$14,772,274","MarketCap":"$0"},{"Date":"Sep 17, 2019","Open":"$0.09052","High":"$0.1003","Low":"$0.08005","Close":"$0.08692","Volume":"$14,772,274","MarketCap":"$0"},{"Date":"Sep 17, 2019","Open":"$0.09052","High":"$0.1003","Low":"$0.08005","Close":"$0.08692","Volume":"$14,772,274","MarketCap":"$0"},{"Date":"Sep 17, 2019","Open":"$0.09052","High":"$0.1003","Low":"$0.08005","Close":"$0.08692","Volume":"$14,772,274","MarketCap":"$0"},{"Date":"Sep 17, 2019","Open":"$0.09052","High":"$0.1003","Low":"$0.08005","Close":"$0.08692","Volume":"$14,772,274","MarketCap":"$0"},{"Date":"Sep 17, 2019","Open":"$0.09052","High":"$0.1003","Low":"$0.08005","Close":"$0.08692","Volume":"$14,772,274","MarketCap":"$0"},{"Date":"Sep 17, 2019","Open":"$0.09052","High":"$0.1003","Low":"$0.08005","Close":"$0.08692","Volume":"$14,772,274","MarketCap":"$0"},{"Date":"Sep 17, 2019","Open":"$0.09052","High":"$0.1003","Low":"$0.08005","Close":"$0.08692","Volume":"$14,772,274","MarketCap":"$0"},{"Date":"Sep 17, 2019","Open":"$0.09052","High":"$0.1003","Low":"$0.08005","Close":"$0.08692","Volume":"$14,772,274","MarketCap":"$0"},{"Date":"Sep 17, 2019","Open":"$0.09052","High":"$0.1003","Low":"$0.08005","Close":"$0.08692","Volume":"$14,772,274","MarketCap":"$0"},{"Date":"Sep 17, 2019","Open":"$0.09052","High":"$0.1003","Low":"$0.08005","Close":"$0.08692","Volume":"$14,772,274","MarketCap":"$0"},{"Date":"Sep 17, 2019","Open":"$0.09052","High":"$0.1003","Low":"$0.08005","Close":"$0.08692","Volume":"$14,772,274","MarketCap":"$0"},{"Date":"Sep 17, 2019","Open":"$0.09052","High":"$0.1003","Low":"$0.08005","Close":"$0.08692","Volume":"$14,772,274","MarketCap":"$0"},{"Date":"Sep 17, 2019","Open":"$0.09052","High":"$0.1003","Low":"$0.08005","Close":"$0.08692","Volume":"$14,772,274","MarketCap":"$0"},{"Date":"Sep 17, 2019","Open":"$0.09052","High":"$0.1003","Low":"$0.08005","Close":"$0.08692","Volume":"$14,772,274","MarketCap":"$0"},{"Date":"Sep 17, 2019","Open":"$0.09052","High":"$0.1003","Low":"$0.08005","Close":"$0.08692","Volume":"$14,772,274","MarketCap":"$0"},{"Date":"Sep 17, 2019","Open":"$0.09052","High":"$0.1003","Low":"$0.08005","Close":"$0.08692","Volume":"$14,772,274","MarketCap":"$0"},{"Date":"Sep 17, 2019","Open":"$0.09052","High":"$0.1003","Low":"$0.08005","Close":"$0.08692","Volume":"$14,772,274","MarketCap":"$0"},{"Date":"Sep 17, 2019","Open":"$0.09052","High":"$0.1003","Low":"$0.08005","Close":"$0.08692","Volume":"$14,772,274","MarketCap":"$0"},{"Date":"Sep 17, 2019","Open":"$0.09052","High":"$0.1003","Low":"$0.08005","Close":"$0.08692","Volume":"$14,772,274","MarketCap":"$0"},{"Date":"Sep 17, 2019","Open":"$0.09052","High":"$0.1003","Low":"$0.08005","Close":"$0.08692","Volume":"$14,772,274","MarketCap":"$0"},{"Date":"Sep 17, 2019","Open":"$0.09052","High":"$0.1003","Low":"$0.08005","Close":"$0.08692","Volume":"$14,772,274","MarketCap":"$0"},{"Date":"Sep 17, 2019","Open":"$0.09052","High":"$0.1003","Low":"$0.08005","Close":"$0.08692","Volume":"$14,772,274","MarketCap":"$0"},{"Date":"Sep 17, 2019","Open":"$0.09052","High":"$0.1003","Low":"$0.08005","Close":"$0.08692","Volume":"$14,772,274","MarketCap":"$0"},{"Date":"Sep 17, 2019","Open":"$0.09052","High":"$0.1003","Low":"$0.08005","Close":"$0.08692","Volume":"$14,772,274","MarketCap":"$0"},{"Date":"Sep 17, 2019","Open":"$0.09052","High":"$0.1003","Low":"$0.08005","Close":"$0.08692","Volume":"$14,772,274","MarketCap":"$0"},{"Date":"Sep 17, 2019","Open":"$0.09052","High":"$0.1003","Low":"$0.08005","Close":"$0.08692","Volume":"$14,772,274","MarketCap":"$0"},{"Date":"Sep 17, 2019","Open":"$0.09052","High":"$0.1003","Low":"$0.08005","Close":"$0.08692","Volume":"$14,772,274","MarketCap":"$0"},{"Date":"Sep 17, 2019","Open":"$0.09052","High":"$0.1003","Low":"$0.08005","Close":"$0.08692","Volume":"$14,772,274","MarketCap":"$0"},{"Date":"Sep 17, 2019","Open":"$0.09052","High":"$0.1003","Low":"$0.08005","Close":"$0.08692","Volume":"$14,772,274","MarketCap":"$0"},{"Date":"Sep 17, 2019","Open":"$0.09052","High":"$0.1003","Low":"$0.08005","Close":"$0.08692","Volume":"$14,772,274","MarketCap":"$0"},{"Date":"Sep 17, 2019","Open":"$0.09052","High":"$0.1003","Low":"$0.08005","Close":"$0.08692","Volume":"$14,772,274","MarketCap":"$0"},{"Date":"Sep 17, 2019","Open":"$0.09052","High":"$0.1003","Low":"$0.08005","Close":"$0.08692","Volume":"$14,772,274","MarketCap":"$0"},{"Date":"Sep 17, 2019","Open":"$0.09052","High":"$0.1003","Low":"$0.08005","Close":"$0.08692","Volume":"$14,772,274","MarketCap":"$0"},{"Date":"Sep 17, 2019","Open":"$0.09052","High":"$0.1003","Low":"$0.08005","Close":"$0.08692","Volume":"$14,772,274","MarketCap":"$0"},{"Date":"Sep 17, 2019","Open":"$0.09052","High":"$0.1003","Low":"$0.08005","Close":"$0.08692","Volume":"$14,772,274","MarketCap":"$0"},{"Date":"Sep 17, 2019","Open":"$0.09052","High":"$0.1003","Low":"$0.08005","Close":"$0.08692","Volume":"$14,772,274","MarketCap":"$0"},{"Date":"Sep 17, 2019","Open":"$0.09052","High":"$0.1003","Low":"$0.08005","Close":"$0.08692","Volume":"$14,772,274","MarketCap":"$0"},{"Date":"Sep 17, 2019","Open":"$0.09052","High":"$0.1003","Low":"$0.08005","Close":"$0.08692","Volume":"$14,772,274","MarketCap":"$0"},{"Date":"Sep 17, 2019","Open":"$0.09052","High":"$0.1003","Low":"$0.08005","Close":"$0.08692","Volume":"$14,772,274","MarketCap":"$0"},{"Date":"Sep 17, 2019","Open":"$0.09052","High":"$0.1003","Low":"$0.08005","Close":"$0.08692","Volume":"$14,772,274","MarketCap":"$0"},{"Date":"Sep 17, 2019","Open":"$0.09052","High":"$0.1003","Low":"$0.08005","Close":"$0.08692","Volume":"$14,772,274","MarketCap":"$0"},{"Date":"Sep 17, 2019","Open":"$0.09052","High":"$0.1003","Low":"$0.08005","Close":"$0.08692","Volume":"$14,772,274","MarketCap":"$0"},{"Date":"Sep 17, 2019","Open":"$0.09052","High":"$0.1003","Low":"$0.08005","Close":"$0.08692","Volume":"$14,772,274","MarketCap":"$0"},{"Date":"Sep 17, 2019","Open":"$0.09052","High":"$0.1003","Low":"$0.08005","Close":"$0.08692","Volume":"$14,772,274","MarketCap":"$0"},{"Date":"Sep 17, 2019","Open":"$0.09052","High":"$0.1003","Low":"$0.08005","Close":"$0.08692","Volume":"$14,772,274","MarketCap":"$0"},{"Date":"Sep 17, 2019","Open":"$0.09052","High":"$0.1003","Low":"$0.08005","Close":"$0.08692","Volume":"$14,772,274","MarketCap":"$0"},{"Date":"Sep 17, 2019","Open":"$0.09052","High":"$0.1003","Low":"$0.08005","Close":"$0.08692","Volume":"$14,772,274","MarketCap":"$0"},{"Date":"Sep 17, 2019","Open":"$0.09052","High":"$0.1003","Low":"$0.08005","Close":"$0.08692","Volume":"$14,772,274","MarketCap":"$0"},{"Date":"Sep 17, 2019","Open":"$0.09052","High":"$0.1003","Low":"$0.08005","Close":"$0.08692","Volume":"$14,772,274","MarketCap":"$0"},{"Date":"Sep 17, 2019","Open":"$0.09052","High":"$0.1003","Low":"$0.08005","Close":"$0.08692","Volume":"$14,772,274","MarketCap":"$0"},{"Date":"Sep 17, 2019","Open":"$0.09052","High":"$0.1003","Low":"$0.08005","Close":"$0.08692","Volume":"$14,772,274","MarketCap":"$0"},{"Date":"Sep 17, 2019","Open":"$0.09052","High":"$0.1003","Low":"$0.08005","Close":"$0.08692","Volume":"$14,772,274","MarketCap":"$0"},{"Date":"Sep 17, 2019","Open":"$0.09052","High":"$0.1003","Low":"$0.08005","Close":"$0.08692","Volume":"$14,772,274","MarketCap":"$0"},{"Date":"Sep 17, 2019","Open":"$0.09052","High":"$0.1003","Low":"$0.08005","Close":"$0.08692","Volume":"$14,772,274","MarketCap":"$0"},{"Date":"Sep 17, 2019","Open":"$0.09052","High":"$0.1003","Low":"$0.08005","Close":"$0.08692","Volume":"$14,772,274","MarketCap":"$0"},{"Date":"Sep 17, 2019","Open":"$0.09052","High":"$0.1003","Low":"$0.08005","Close":"$0.08692","Volume":"$14,772,274","MarketCap":"$0"},{"Date":"Sep 17, 2019","Open":"$0.09052","High":"$0.1003","Low":"$0.08005","Close":"$0.08692","Volume":"$14,772,274","MarketCap":"$0"},{"Date":"Sep 17, 2019","Open":"$0.09052","High":"$0.1003","Low":"$0.08005","Close":"$0.08692","Volume":"$14,772,274","MarketCap":"$0"},{"Date":"Sep 17, 2019","Open":"$0.09052","High":"$0.1003","Low":"$0.08005","Close":"$0.08692","Volume":"$14,772,274","MarketCap":"$0"},{"Date":"Sep 17, 2019","Open":"$0.09052","High":"$0.1003","Low":"$0.08005","Close":"$0.08692","Volume":"$14,772,274","MarketCap":"$0"},{"Date":"Sep 17, 2019","Open":"$0.09052","High":"$0.1003","Low":"$0.08005","Close":"$0.08692","Volume":"$14,772,274","MarketCap":"$0"},{"Date":"Sep 17, 2019","Open":"$0.09052","High":"$0.1003","Low":"$0.08005","Close":"$0.08692","Volume":"$14,772,274","MarketCap":"$0"},{"Date":"Sep 17, 2019","Open":"$0.09052","High":"$0.1003","Low":"$0.08005","Close":"$0.08692","Volume":"$14,772,274","MarketCap":"$0"},{"Date":"Sep 17, 2019","Open":"$0.09052","High":"$0.1003","Low":"$0.08005","Close":"$0.08692","Volume":"$14,772,274","MarketCap":"$0"},{"Date":"Sep 17, 2019","Open":"$0.09052","High":"$0.1003","Low":"$0.08005","Close":"$0.08692","Volume":"$14,772,274","MarketCap":"$0"},{"Date":"Sep 17, 2019","Open":"$0.09052","High":"$0.1003","Low":"$0.08005","Close":"$0.08692","Volume":"$14,772,274","MarketCap":"$0"},{"Date":"Sep 17, 2019","Open":"$0.09052","High":"$0.1003","Low":"$0.08005","Close":"$0.08692","Volume":"$14,772,274","MarketCap":"$0"},{"Date":"Sep 17, 2019","Open":"$0.09052","High":"$0.1003","Low":"$0.08005","Close":"$0.08692","Volume":"$14,772,274","MarketCap":"$0"},{"Date":"Sep 17, 2019","Open":"$0.09052","High":"$0.1003","Low":"$0.08005","Close":"$0.08692","Volume":"$14,772,274","MarketCap":"$0"},{"Date":"Sep 17, 2019","Open":"$0.09052","High":"$0.1003","Low":"$0.08005","Close":"$0.08692","Volume":"$14,772,274","MarketCap":"$0"},{"Date":"Sep 17, 2019","Open":"$0.09052","High":"$0.1003","Low":"$0.08005","Close":"$0.08692","Volume":"$14,772,274","MarketCap":"$0"},{"Date":"Sep 17, 2019","Open":"$0.09052","High":"$0.1003","Low":"$0.08005","Close":"$0.08692","Volume":"$14,772,274","MarketCap":"$0"},{"Date":"Sep 17, 2019","Open":"$0.09052","High":"$0.1003","Low":"$0.08005","Close":"$0.08692","Volume":"$14,772,274","MarketCap":"$0"},{"Date":"Sep 17, 2019","Open":"$0.09052","High":"$0.1003","Low":"$0.08005","Close":"$0.08692","Volume":"$14,772,274","MarketCap":"$0"},{"Date":"Sep 17, 2019","Open":"$0.09052","High":"$0.1003","Low":"$0.08005","Close":"$0.08692","Volume":"$14,772,274","MarketCap":"$0"},{"Date":"Sep 17, 2019","Open":"$0.09052","High":"$0.1003","Low":"$0.08005","Close":"$0.08692","Volume":"$14,772,274","MarketCap":"$0"},{"Date":"Sep 17, 2019","Open":"$0.09052","High":"$0.1003","Low":"$0.08005","Close":"$0.08692","Volume":"$14,772,274","MarketCap":"$0"},{"Date":"Sep 17, 2019","Open":"$0.09052","High":"$0.1003","Low":"$0.08005","Close":"$0.08692","Volume":"$14,772,274","MarketCap":"$0"},{"Date":"Sep 17, 2019","Open":"$0.09052","High":"$0.1003","Low":"$0.08005","Close":"$0.08692","Volume":"$14,772,274","MarketCap":"$0"},{"Date":"Sep 17, 2019","Open":"$0.09052","High":"$0.1003","Low":"$0.08005","Close":"$0.08692","Volume":"$14,772,274","MarketCap":"$0"},{"Date":"Sep 17, 2019","Open":"$0.09052","High":"$0.1003","Low":"$0.08005","Close":"$0.08692","Volume":"$14,772,274","MarketCap":"$0"},{"Date":"Sep 17, 2019","Open":"$0.09052","High":"$0.1003","Low":"$0.08005","Close":"$0.08692","Volume":"$14,772,274","MarketCap":"$0"},{"Date":"Sep 17, 2019","Open":"$0.09052","High":"$0.1003","Low":"$0.08005","Close":"$0.08692","Volume":"$14,772,274","MarketCap":"$0"},{"Date":"Sep 17, 2019","Open":"$0.09052","High":"$0.1003","Low":"$0.08005","Close":"$0.08692","Volume":"$14,772,274","MarketCap":"$0"},{"Date":"Sep 17, 2019","Open":"$0.09052","High":"$0.1003","Low":"$0.08005","Close":"$0.08692","Volume":"$14,772,274","MarketCap":"$0"},{"Date":"Sep 17, 2019","Open":"$0.09052","High":"$0.1003","Low":"$0.08005","Close":"$0.08692","Volume":"$14,772,274","MarketCap":"$0"},{"Date":"Sep 17, 2019","Open":"$0.09052","High":"$0.1003","Low":"$0.08005","Close":"$0.08692","Volume":"$14,772,274","MarketCap":"$0"},{"Date":"Sep 17, 2019","Open":"$0.09052","High":"$0.1003","Low":"$0.08005","Close":"$0.08692","Volume":"$14,772,274","MarketCap":"$0"},{"Date":"Sep 17, 2019","Open":"$0.09052","High":"$0.1003","Low":"$0.08005","Close":"$0.08692","Volume":"$14,772,274","MarketCap":"$0"},{"Date":"Sep 17, 2019","Open":"$0.09052","High":"$0.1003","Low":"$0.08005","Close":"$0.08692","Volume":"$14,772,274","MarketCap":"$0"},{"Date":"Sep 17, 2019","Open":"$0.09052","High":"$0.1003","Low":"$0.08005","Close":"$0.08692","Volume":"$14,772,274","MarketCap":"$0"},{"Date":"Sep 17, 2019","Open":"$0.09052","High":"$0.1003","Low":"$0.08005","Close":"$0.08692","Volume":"$14,772,274","MarketCap":"$0"},{"Date":"Sep 17, 2019","Open":"$0.09052","High":"$0.1003","Low":"$0.08005","Close":"$0.08692","Volume":"$14,772,274","MarketCap":"$0"},{"Date":"Sep 17, 2019","Open":"$0.09052","High":"$0.1003","Low":"$0.08005","Close":"$0.08692","Volume":"$14,772,274","MarketCap":"$0"},{"Date":"Sep 17, 2019","Open":"$0.09052","High":"$0.1003","Low":"$0.08005","Close":"$0.08692","Volume":"$14,772,274","MarketCap":"$0"},{"Date":"Sep 17, 2019","Open":"$0.09052","High":"$0.1003","Low":"$0.08005","Close":"$0.08692","Volume":"$14,772,274","MarketCap":"$0"},{"Date":"Sep 17, 2019","Open":"$0.09052","High":"$0.1003","Low":"$0.08005","Close":"$0.08692","Volume":"$14,772,274","MarketCap":"$0"},{"Date":"Sep 17, 2019","Open":"$0.09052","High":"$0.1003","Low":"$0.08005","Close":"$0.08692","Volume":"$14,772,274","MarketCap":"$0"},{"Date":"Sep 17, 2019","Open":"$0.09052","High":"$0.1003","Low":"$0.08005","Close":"$0.08692","Volume":"$14,772,274","MarketCap":"$0"},{"Date":"Sep 17, 2019","Open":"$0.09052","High":"$0.1003","Low":"$0.08005","Close":"$0.08692","Volume":"$14,772,274","MarketCap":"$0"},{"Date":"Sep 17, 2019","Open":"$0.09052","High":"$0.1003","Low":"$0.08005","Close":"$0.08692","Volume":"$14,772,274","MarketCap":"$0"},{"Date":"Sep 17, 2019","Open":"$0.09052","High":"$0.1003","Low":"$0.08005","Close":"$0.08692","Volume":"$14,772,274","MarketCap":"$0"},{"Date":"Sep 17, 2019","Open":"$0.09052","High":"$0.1003","Low":"$0.08005","Close":"$0.08692","Volume":"$14,772,274","MarketCap":"$0"},{"Date":"Sep 17, 2019","Open":"$0.09052","High":"$0.1003","Low":"$0.08005","Close":"$0.08692","Volume":"$14,772,274","MarketCap":"$0"},{"Date":"Sep 17, 2019","Open":"$0.09052","High":"$0.1003","Low":"$0.08005","Close":"$0.08692","Volume":"$14,772,274","MarketCap":"$0"},{"Date":"Sep 17, 2019","Open":"$0.09052","High":"$0.1003","Low":"$0.08005","Close":"$0.08692","Volume":"$14,772,274","MarketCap":"$0"},{"Date":"Sep 17, 2019","Open":"$0.09052","High":"$0.1003","Low":"$0.08005","Close":"$0.08692","Volume":"$14,772,274","MarketCap":"$0"},{"Date":"Sep 17, 2019","Open":"$0.09052","High":"$0.1003","Low":"$0.08005","Close":"$0.08692","Volume":"$14,772,274","MarketCap":"$0"},{"Date":"Sep 17, 2019","Open":"$0.09052","High":"$0.1003","Low":"$0.08005","Close":"$0.08692","Volume":"$14,772,274","MarketCap":"$0"},{"Date":"Sep 17, 2019","Open":"$0.09052","High":"$0.1003","Low":"$0.08005","Close":"$0.08692","Volume":"$14,772,274","MarketCap":"$0"},{"Date":"Sep 17, 2019","Open":"$0.09052","High":"$0.1003","Low":"$0.08005","Close":"$0.08692","Volume":"$14,772,274","MarketCap":"$0"},{"Date":"Sep 17, 2019","Open":"$0.09052","High":"$0.1003","Low":"$0.08005","Close":"$0.08692","Volume":"$14,772,274","MarketCap":"$0"},{"Date":"Sep 17, 2019","Open":"$0.09052","High":"$0.1003","Low":"$0.08005","Close":"$0.08692","Volume":"$14,772,274","MarketCap":"$0"},{"Date":"Sep 17, 2019","Open":"$0.09052","High":"$0.1003","Low":"$0.08005","Close":"$0.08692","Volume":"$14,772,274","MarketCap":"$0"},{"Date":"Sep 17, 2019","Open":"$0.09052","High":"$0.1003","Low":"$0.08005","Close":"$0.08692","Volume":"$14,772,274","MarketCap":"$0"},{"Date":"Sep 17, 2019","Open":"$0.09052","High":"$0.1003","Low":"$0.08005","Close":"$0.08692","Volume":"$14,772,274","MarketCap":"$0"},{"Date":"Sep 17, 2019","Open":"$0.09052","High":"$0.1003","Low":"$0.08005","Close":"$0.08692","Volume":"$14,772,274","MarketCap":"$0"},{"Date":"Sep 17, 2019","Open":"$0.09052","High":"$0.1003","Low":"$0.08005","Close":"$0.08692","Volume":"$14,772,274","MarketCap":"$0"},{"Date":"Sep 17, 2019","Open":"$0.09052","High":"$0.1003","Low":"$0.08005","Close":"$0.08692","Volume":"$14,772,274","MarketCap":"$0"},{"Date":"Sep 17, 2019","Open":"$0.09052","High":"$0.1003","Low":"$0.08005","Close":"$0.08692","Volume":"$14,772,274","MarketCap":"$0"},{"Date":"Sep 17, 2019","Open":"$0.09052","High":"$0.1003","Low":"$0.08005","Close":"$0.08692","Volume":"$14,772,274","MarketCap":"$0"},{"Date":"Sep 17, 2019","Open":"$0.09052","High":"$0.1003","Low":"$0.08005","Close":"$0.08692","Volume":"$14,772,274","MarketCap":"$0"},{"Date":"Sep 17, 2019","Open":"$0.09052","High":"$0.1003","Low":"$0.08005","Close":"$0.08692","Volume":"$14,772,274","MarketCap":"$0"},{"Date":"Sep 17, 2019","Open":"$0.09052","High":"$0.1003","Low":"$0.08005","Close":"$0.08692","Volume":"$14,772,274","MarketCap":"$0"},{"Date":"Sep 17, 2019","Open":"$0.09052","High":"$0.1003","Low":"$0.08005","Close":"$0.08692","Volume":"$14,772,274","MarketCap":"$0"},{"Date":"Sep 17, 2019","Open":"$0.09052","High":"$0.1003","Low":"$0.08005","Close":"$0.08692","Volume":"$14,772,274","MarketCap":"$0"},{"Date":"Sep 17, 2019","Open":"$0.09052","High":"$0.1003","Low":"$0.08005","Close":"$0.08692","Volume":"$14,772,274","MarketCap":"$0"},{"Date":"Sep 17, 2019","Open":"$0.09052","High":"$0.1003","Low":"$0.08005","Close":"$0.08692","Volume":"$14,772,274","MarketCap":"$0"},{"Date":"Sep 17, 2019","Open":"$0.09052","High":"$0.1003","Low":"$0.08005","Close":"$0.08692","Volume":"$14,772,274","MarketCap":"$0"},{"Date":"Sep 17, 2019","Open":"$0.09052","High":"$0.1003","Low":"$0.08005","Close":"$0.08692","Volume":"$14,772,274","MarketCap":"$0"},{"Date":"Sep 17, 2019","Open":"$0.09052","High":"$0.1003","Low":"$0.08005","Close":"$0.08692","Volume":"$14,772,274","MarketCap":"$0"},{"Date":"Sep 17, 2019","Open":"$0.09052","High":"$0.1003","Low":"$0.08005","Close":"$0.08692","Volume":"$14,772,274","MarketCap":"$0"},{"Date":"Sep 17, 2019","Open":"$0.09052","High":"$0.1003","Low":"$0.08005","Close":"$0.08692","Volume":"$14,772,274","MarketCap":"$0"},{"Date":"Sep 17, 2019","Open":"$0.09052","High":"$0.1003","Low":"$0.08005","Close":"$0.08692","Volume":"$14,772,274","MarketCap":"$0"},{"Date":"Sep 17, 2019","Open":"$0.09052","High":"$0.1003","Low":"$0.08005","Close":"$0.08692","Volume":"$14,772,274","MarketCap":"$0"},{"Date":"Sep 17, 2019","Open":"$0.09052","High":"$0.1003","Low":"$0.08005","Close":"$0.08692","Volume":"$14,772,274","MarketCap":"$0"},{"Date":"Sep 17, 2019","Open":"$0.09052","High":"$0.1003","Low":"$0.08005","Close":"$0.08692","Volume":"$14,772,274","MarketCap":"$0"},{"Date":"Sep 17, 2019","Open":"$0.09052","High":"$0.1003","Low":"$0.08005","Close":"$0.08692","Volume":"$14,772,274","MarketCap":"$0"},{"Date":"Sep 17, 2019","Open":"$0.09052","High":"$0.1003","Low":"$0.08005","Close":"$0.08692","Volume":"$14,772,274","MarketCap":"$0"},{"Date":"Sep 17, 2019","Open":"$0.09052","High":"$0.1003","Low":"$0.08005","Close":"$0.08692","Volume":"$14,772,274","MarketCap":"$0"},{"Date":"Sep 17, 2019","Open":"$0.09052","High":"$0.1003","Low":"$0.08005","Close":"$0.08692","Volume":"$14,772,274","MarketCap":"$0"},{"Date":"Sep 17, 2019","Open":"$0.09052","High":"$0.1003","Low":"$0.08005","Close":"$0.08692","Volume":"$14,772,274","MarketCap":"$0"},{"Date":"Sep 17, 2019","Open":"$0.09052","High":"$0.1003","Low":"$0.08005","Close":"$0.08692","Volume":"$14,772,274","MarketCap":"$0"},{"Date":"Sep 17, 2019","Open":"$0.09052","High":"$0.1003","Low":"$0.08005","Close":"$0.08692","Volume":"$14,772,274","MarketCap":"$0"},{"Date":"Sep 17, 2019","Open":"$0.09052","High":"$0.1003","Low":"$0.08005","Close":"$0.08692","Volume":"$14,772,274","MarketCap":"$0"},{"Date":"Sep 17, 2019","Open":"$0.09052","High":"$0.1003","Low":"$0.08005","Close":"$0.08692","Volume":"$14,772,274","MarketCap":"$0"},{"Date":"Sep 17, 2019","Open":"$0.09052","High":"$0.1003","Low":"$0.08005","Close":"$0.08692","Volume":"$14,772,274","MarketCap":"$0"},{"Date":"Sep 17, 2019","Open":"$0.09052","High":"$0.1003","Low":"$0.08005","Close":"$0.08692","Volume":"$14,772,274","MarketCap":"$0"},{"Date":"Sep 17, 2019","Open":"$0.09052","High":"$0.1003","Low":"$0.08005","Close":"$0.08692","Volume":"$14,772,274","MarketCap":"$0"},{"Date":"Sep 17, 2019","Open":"$0.09052","High":"$0.1003","Low":"$0.08005","Close":"$0.08692","Volume":"$14,772,274","MarketCap":"$0"},{"Date":"Sep 17, 2019","Open":"$0.09052","High":"$0.1003","Low":"$0.08005","Close":"$0.08692","Volume":"$14,772,274","MarketCap":"$0"},{"Date":"Sep 17, 2019","Open":"$0.09052","High":"$0.1003","Low":"$0.08005","Close":"$0.08692","Volume":"$14,772,274","MarketCap":"$0"},{"Date":"Sep 17, 2019","Open":"$0.09052","High":"$0.1003","Low":"$0.08005","Close":"$0.08692","Volume":"$14,772,274","MarketCap":"$0"},{"Date":"Sep 17, 2019","Open":"$0.09052","High":"$0.1003","Low":"$0.08005","Close":"$0.08692","Volume":"$14,772,274","MarketCap":"$0"},{"Date":"Sep 17, 2019","Open":"$0.09052","High":"$0.1003","Low":"$0.08005","Close":"$0.08692","Volume":"$14,772,274","MarketCap":"$0"},{"Date":"Sep 17, 2019","Open":"$0.09052","High":"$0.1003","Low":"$0.08005","Close":"$0.08692","Volume":"$14,772,274","MarketCap":"$0"},{"Date":"Sep 17, 2019","Open":"$0.09052","High":"$0.1003","Low":"$0.08005","Close":"$0.08692","Volume":"$14,772,274","MarketCap":"$0"},{"Date":"Sep 17, 2019","Open":"$0.09052","High":"$0.1003","Low":"$0.08005","Close":"$0.08692","Volume":"$14,772,274","MarketCap":"$0"},{"Date":"Sep 17, 2019","Open":"$0.09052","High":"$0.1003","Low":"$0.08005","Close":"$0.08692","Volume":"$14,772,274","MarketCap":"$0"},{"Date":"Sep 17, 2019","Open":"$0.09052","High":"$0.1003","Low":"$0.08005","Close":"$0.08692","Volume":"$14,772,274","MarketCap":"$0"},{"Date":"Sep 17, 2019","Open":"$0.09052","High":"$0.1003","Low":"$0.08005","Close":"$0.08692","Volume":"$14,772,274","MarketCap":"$0"},{"Date":"Sep 17, 2019","Open":"$0.09052","High":"$0.1003","Low":"$0.08005","Close":"$0.08692","Volume":"$14,772,274","MarketCap":"$0"},{"Date":"Sep 17, 2019","Open":"$0.09052","High":"$0.1003","Low":"$0.08005","Close":"$0.08692","Volume":"$14,772,274","MarketCap":"$0"},{"Date":"Sep 17, 2019","Open":"$0.09052","High":"$0.1003","Low":"$0.08005","Close":"$0.08692","Volume":"$14,772,274","MarketCap":"$0"},{"Date":"Sep 17, 2019","Open":"$0.09052","High":"$0.1003","Low":"$0.08005","Close":"$0.08692","Volume":"$14,772,274","MarketCap":"$0"},{"Date":"Sep 17, 2019","Open":"$0.09052","High":"$0.1003","Low":"$0.08005","Close":"$0.08692","Volume":"$14,772,274","MarketCap":"$0"},{"Date":"Sep 17, 2019","Open":"$0.09052","High":"$0.1003","Low":"$0.08005","Close":"$0.08692","Volume":"$14,772,274","MarketCap":"$0"},{"Date":"Sep 17, 2019","Open":"$0.09052","High":"$0.1003","Low":"$0.08005","Close":"$0.08692","Volume":"$14,772,274","MarketCap":"$0"},{"Date":"Sep 17, 2019","Open":"$0.09052","High":"$0.1003","Low":"$0.08005","Close":"$0.08692","Volume":"$14,772,274","MarketCap":"$0"},{"Date":"Sep 17, 2019","Open":"$0.09052","High":"$0.1003","Low":"$0.08005","Close":"$0.08692","Volume":"$14,772,274","MarketCap":"$0"},{"Date":"Sep 17, 2019","Open":"$0.09052","High":"$0.1003","Low":"$0.08005","Close":"$0.08692","Volume":"$14,772,274","MarketCap":"$0"},{"Date":"Sep 17, 2019","Open":"$0.09052","High":"$0.1003","Low":"$0.08005","Close":"$0.08692","Volume":"$14,772,274","MarketCap":"$0"},{"Date":"Sep 17, 2019","Open":"$0.09052","High":"$0.1003","Low":"$0.08005","Close":"$0.08692","Volume":"$14,772,274","MarketCap":"$0"},{"Date":"Sep 17, 2019","Open":"$0.09052","High":"$0.1003","Low":"$0.08005","Close":"$0.08692","Volume":"$14,772,274","MarketCap":"$0"},{"Date":"Sep 17, 2019","Open":"$0.09052","High":"$0.1003","Low":"$0.08005","Close":"$0.08692","Volume":"$14,772,274","MarketCap":"$0"},{"Date":"Sep 17, 2019","Open":"$0.09052","High":"$0.1003","Low":"$0.08005","Close":"$0.08692","Volume":"$14,772,274","MarketCap":"$0"},{"Date":"Sep 17, 2019","Open":"$0.09052","High":"$0.1003","Low":"$0.08005","Close":"$0.08692","Volume":"$14,772,274","MarketCap":"$0"},{"Date":"Sep 17, 2019","Open":"$0.09052","High":"$0.1003","Low":"$0.08005","Close":"$0.08692","Volume":"$14,772,274","MarketCap":"$0"},{"Date":"Sep 17, 2019","Open":"$0.09052","High":"$0.1003","Low":"$0.08005","Close":"$0.08692","Volume":"$14,772,274","MarketCap":"$0"},{"Date":"Sep 17, 2019","Open":"$0.09052","High":"$0.1003","Low":"$0.08005","Close":"$0.08692","Volume":"$14,772,274","MarketCap":"$0"},{"Date":"Sep 17, 2019","Open":"$0.09052","High":"$0.1003","Low":"$0.08005","Close":"$0.08692","Volume":"$14,772,274","MarketCap":"$0"},{"Date":"Sep 17, 2019","Open":"$0.09052","High":"$0.1003","Low":"$0.08005","Close":"$0.08692","Volume":"$14,772,274","MarketCap":"$0"},{"Date":"Sep 17, 2019","Open":"$0.09052","High":"$0.1003","Low":"$0.08005","Close":"$0.08692","Volume":"$14,772,274","MarketCap":"$0"},{"Date":"Sep 17, 2019","Open":"$0.09052","High":"$0.1003","Low":"$0.08005","Close":"$0.08692","Volume":"$14,772,274","MarketCap":"$0"},{"Date":"Sep 17, 2019","Open":"$0.09052","High":"$0.1003","Low":"$0.08005","Close":"$0.08692","Volume":"$14,772,274","MarketCap":"$0"},{"Date":"Sep 17, 2019","Open":"$0.09052","High":"$0.1003","Low":"$0.08005","Close":"$0.08692","Volume":"$14,772,274","MarketCap":"$0"},{"Date":"Sep 17, 2019","Open":"$0.09052","High":"$0.1003","Low":"$0.08005","Close":"$0.08692","Volume":"$14,772,274","MarketCap":"$0"},{"Date":"Sep 17, 2019","Open":"$0.09052","High":"$0.1003","Low":"$0.08005","Close":"$0.08692","Volume":"$14,772,274","MarketCap":"$0"},{"Date":"Sep 17, 2019","Open":"$0.09052","High":"$0.1003","Low":"$0.08005","Close":"$0.08692","Volume":"$14,772,274","MarketCap":"$0"},{"Date":"Sep 17, 2019","Open":"$0.09052","High":"$0.1003","Low":"$0.08005","Close":"$0.08692","Volume":"$14,772,274","MarketCap":"$0"},{"Date":"Sep 17, 2019","Open":"$0.09052","High":"$0.1003","Low":"$0.08005","Close":"$0.08692","Volume":"$14,772,274","MarketCap":"$0"},{"Date":"Sep 17, 2019","Open":"$0.09052","High":"$0.1003","Low":"$0.08005","Close":"$0.08692","Volume":"$14,772,274","MarketCap":"$0"},{"Date":"Sep 17, 2019","Open":"$0.09052","High":"$0.1003","Low":"$0.08005","Close":"$0.08692","Volume":"$14,772,274","MarketCap":"$0"},{"Date":"Sep 17, 2019","Open":"$0.09052","High":"$0.1003","Low":"$0.08005","Close":"$0.08692","Volume":"$14,772,274","MarketCap":"$0"},{"Date":"Sep 17, 2019","Open":"$0.09052","High":"$0.1003","Low":"$0.08005","Close":"$0.08692","Volume":"$14,772,274","MarketCap":"$0"},{"Date":"Sep 17, 2019","Open":"$0.09052","High":"$0.1003","Low":"$0.08005","Close":"$0.08692","Volume":"$14,772,274","MarketCap":"$0"},{"Date":"Sep 17, 2019","Open":"$0.09052","High":"$0.1003","Low":"$0.08005","Close":"$0.08692","Volume":"$14,772,274","MarketCap":"$0"},{"Date":"Sep 17, 2019","Open":"$0.09052","High":"$0.1003","Low":"$0.08005","Close":"$0.08692","Volume":"$14,772,274","MarketCap":"$0"},{"Date":"Sep 17, 2019","Open":"$0.09052","High":"$0.1003","Low":"$0.08005","Close":"$0.08692","Volume":"$14,772,274","MarketCap":"$0"},{"Date":"Sep 17, 2019","Open":"$0.09052","High":"$0.1003","Low":"$0.08005","Close":"$0.08692","Volume":"$14,772,274","MarketCap":"$0"},{"Date":"Sep 17, 2019","Open":"$0.09052","High":"$0.1003","Low":"$0.08005","Close":"$0.08692","Volume":"$14,772,274","MarketCap":"$0"},{"Date":"Sep 17, 2019","Open":"$0.09052","High":"$0.1003","Low":"$0.08005","Close":"$0.08692","Volume":"$14,772,274","MarketCap":"$0"},{"Date":"Sep 17, 2019","Open":"$0.09052","High":"$0.1003","Low":"$0.08005","Close":"$0.08692","Volume":"$14,772,274","MarketCap":"$0"},{"Date":"Sep 17, 2019","Open":"$0.09052","High":"$0.1003","Low":"$0.08005","Close":"$0.08692","Volume":"$14,772,274","MarketCap":"$0"},{"Date":"Sep 17, 2019","Open":"$0.09052","High":"$0.1003","Low":"$0.08005","Close":"$0.08692","Volume":"$14,772,274","MarketCap":"$0"},{"Date":"Sep 17, 2019","Open":"$0.09052","High":"$0.1003","Low":"$0.08005","Close":"$0.08692","Volume":"$14,772,274","MarketCap":"$0"},{"Date":"Sep 17, 2019","Open":"$0.09052","High":"$0.1003","Low":"$0.08005","Close":"$0.08692","Volume":"$14,772,274","MarketCap":"$0"},{"Date":"Sep 17, 2019","Open":"$0.09052","High":"$0.1003","Low":"$0.08005","Close":"$0.08692","Volume":"$14,772,274","MarketCap":"$0"},{"Date":"Sep 17, 2019","Open":"$0.09052","High":"$0.1003","Low":"$0.08005","Close":"$0.08692","Volume":"$14,772,274","MarketCap":"$0"},{"Date":"Sep 17, 2019","Open":"$0.09052","High":"$0.1003","Low":"$0.08005","Close":"$0.08692","Volume":"$14,772,274","MarketCap":"$0"},{"Date":"Sep 17, 2019","Open":"$0.09052","High":"$0.1003","Low":"$0.08005","Close":"$0.08692","Volume":"$14,772,274","MarketCap":"$0"},{"Date":"Sep 17, 2019","Open":"$0.09052","High":"$0.1003","Low":"$0.08005","Close":"$0.08692","Volume":"$14,772,274","MarketCap":"$0"},{"Date":"Sep 17, 2019","Open":"$0.09052","High":"$0.1003","Low":"$0.08005","Close":"$0.08692","Volume":"$14,772,274","MarketCap":"$0"},{"Date":"Sep 17, 2019","Open":"$0.09052","High":"$0.1003","Low":"$0.08005","Close":"$0.08692","Volume":"$14,772,274","MarketCap":"$0"},{"Date":"Sep 17, 2019","Open":"$0.09052","High":"$0.1003","Low":"$0.08005","Close":"$0.08692","Volume":"$14,772,274","MarketCap":"$0"},{"Date":"Sep 17, 2019","Open":"$0.09052","High":"$0.1003","Low":"$0.08005","Close":"$0.08692","Volume":"$14,772,274","MarketCap":"$0"},{"Date":"Sep 17, 2019","Open":"$0.09052","High":"$0.1003","Low":"$0.08005","Close":"$0.08692","Volume":"$14,772,274","MarketCap":"$0"},{"Date":"Sep 17, 2019","Open":"$0.09052","High":"$0.1003","Low":"$0.08005","Close":"$0.08692","Volume":"$14,772,274","MarketCap":"$0"},{"Date":"Sep 17, 2019","Open":"$0.09052","High":"$0.1003","Low":"$0.08005","Close":"$0.08692","Volume":"$14,772,274","MarketCap":"$0"},{"Date":"Sep 17, 2019","Open":"$0.09052","High":"$0.1003","Low":"$0.08005","Close":"$0.08692","Volume":"$14,772,274","MarketCap":"$0"},{"Date":"Sep 17, 2019","Open":"$0.09052","High":"$0.1003","Low":"$0.08005","Close":"$0.08692","Volume":"$14,772,274","MarketCap":"$0"},{"Date":"Sep 17, 2019","Open":"$0.09052","High":"$0.1003","Low":"$0.08005","Close":"$0.08692","Volume":"$14,772,274","MarketCap":"$0"},{"Date":"Sep 17, 2019","Open":"$0.09052","High":"$0.1003","Low":"$0.08005","Close":"$0.08692","Volume":"$14,772,274","MarketCap":"$0"},{"Date":"Sep 17, 2019","Open":"$0.09052","High":"$0.1003","Low":"$0.08005","Close":"$0.08692","Volume":"$14,772,274","MarketCap":"$0"},{"Date":"Sep 17, 2019","Open":"$0.09052","High":"$0.1003","Low":"$0.08005","Close":"$0.08692","Volume":"$14,772,274","MarketCap":"$0"},{"Date":"Sep 17, 2019","Open":"$0.09052","High":"$0.1003","Low":"$0.08005","Close":"$0.08692","Volume":"$14,772,274","MarketCap":"$0"},{"Date":"Sep 17, 2019","Open":"$0.09052","High":"$0.1003","Low":"$0.08005","Close":"$0.08692","Volume":"$14,772,274","MarketCap":"$0"},{"Date":"Sep 17, 2019","Open":"$0.09052","High":"$0.1003","Low":"$0.08005","Close":"$0.08692","Volume":"$14,772,274","MarketCap":"$0"},{"Date":"Sep 17, 2019","Open":"$0.09052","High":"$0.1003","Low":"$0.08005","Close":"$0.08692","Volume":"$14,772,274","MarketCap":"$0"},{"Date":"Sep 17, 2019","Open":"$0.09052","High":"$0.1003","Low":"$0.08005","Close":"$0.08692","Volume":"$14,772,274","MarketCap":"$0"},{"Date":"Sep 17, 2019","Open":"$0.09052","High":"$0.1003","Low":"$0.08005","Close":"$0.08692","Volume":"$14,772,274","MarketCap":"$0"},{"Date":"Sep 17, 2019","Open":"$0.09052","High":"$0.1003","Low":"$0.08005","Close":"$0.08692","Volume":"$14,772,274","MarketCap":"$0"},{"Date":"Sep 17, 2019","Open":"$0.09052","High":"$0.1003","Low":"$0.08005","Close":"$0.08692","Volume":"$14,772,274","MarketCap":"$0"},{"Date":"Sep 17, 2019","Open":"$0.09052","High":"$0.1003","Low":"$0.08005","Close":"$0.08692","Volume":"$14,772,274","MarketCap":"$0"},{"Date":"Sep 17, 2019","Open":"$0.09052","High":"$0.1003","Low":"$0.08005","Close":"$0.08692","Volume":"$14,772,274","MarketCap":"$0"},{"Date":"Sep 17, 2019","Open":"$0.09052","High":"$0.1003","Low":"$0.08005","Close":"$0.08692","Volume":"$14,772,274","MarketCap":"$0"},{"Date":"Sep 17, 2019","Open":"$0.09052","High":"$0.1003","Low":"$0.08005","Close":"$0.08692","Volume":"$14,772,274","MarketCap":"$0"},{"Date":"Sep 17, 2019","Open":"$0.09052","High":"$0.1003","Low":"$0.08005","Close":"$0.08692","Volume":"$14,772,274","MarketCap":"$0"},{"Date":"Sep 17, 2019","Open":"$0.09052","High":"$0.1003","Low":"$0.08005","Close":"$0.08692","Volume":"$14,772,274","MarketCap":"$0"},{"Date":"Sep 17, 2019","Open":"$0.09052","High":"$0.1003","Low":"$0.08005","Close":"$0.08692","Volume":"$14,772,274","MarketCap":"$0"},{"Date":"Sep 17, 2019","Open":"$0.09052","High":"$0.1003","Low":"$0.08005","Close":"$0.08692","Volume":"$14,772,274","MarketCap":"$0"},{"Date":"Sep 17, 2019","Open":"$0.09052","High":"$0.1003","Low":"$0.08005","Close":"$0.08692","Volume":"$14,772,274","MarketCap":"$0"},{"Date":"Sep 17, 2019","Open":"$0.09052","High":"$0.1003","Low":"$0.08005","Close":"$0.08692","Volume":"$14,772,274","MarketCap":"$0"},{"Date":"Sep 17, 2019","Open":"$0.09052","High":"$0.1003","Low":"$0.08005","Close":"$0.08692","Volume":"$14,772,274","MarketCap":"$0"},{"Date":"Sep 17, 2019","Open":"$0.09052","High":"$0.1003","Low":"$0.08005","Close":"$0.08692","Volume":"$14,772,274","MarketCap":"$0"},{"Date":"Sep 17, 2019","Open":"$0.09052","High":"$0.1003","Low":"$0.08005","Close":"$0.08692","Volume":"$14,772,274","MarketCap":"$0"},{"Date":"Sep 17, 2019","Open":"$0.09052","High":"$0.1003","Low":"$0.08005","Close":"$0.08692","Volume":"$14,772,274","MarketCap":"$0"},{"Date":"Sep 17, 2019","Open":"$0.09052","High":"$0.1003","Low":"$0.08005","Close":"$0.08692","Volume":"$14,772,274","MarketCap":"$0"},{"Date":"Sep 17, 2019","Open":"$0.09052","High":"$0.1003","Low":"$0.08005","Close":"$0.08692","Volume":"$14,772,274","MarketCap":"$0"},{"Date":"Sep 17, 2019","Open":"$0.09052","High":"$0.1003","Low":"$0.08005","Close":"$0.08692","Volume":"$14,772,274","MarketCap":"$0"},{"Date":"Sep 17, 2019","Open":"$0.09052","High":"$0.1003","Low":"$0.08005","Close":"$0.08692","Volume":"$14,772,274","MarketCap":"$0"},{"Date":"Sep 17, 2019","Open":"$0.09052","High":"$0.1003","Low":"$0.08005","Close":"$0.08692","Volume":"$14,772,274","MarketCap":"$0"},{"Date":"Sep 17, 2019","Open":"$0.09052","High":"$0.1003","Low":"$0.08005","Close":"$0.08692","Volume":"$14,772,274","MarketCap":"$0"},{"Date":"Sep 17, 2019","Open":"$0.09052","High":"$0.1003","Low":"$0.08005","Close":"$0.08692","Volume":"$14,772,274","MarketCap":"$0"},{"Date":"Sep 17, 2019","Open":"$0.09052","High":"$0.1003","Low":"$0.08005","Close":"$0.08692","Volume":"$14,772,274","MarketCap":"$0"},{"Date":"Sep 17, 2019","Open":"$0.09052","High":"$0.1003","Low":"$0.08005","Close":"$0.08692","Volume":"$14,772,274","MarketCap":"$0"},{"Date":"Sep 17, 2019","Open":"$0.09052","High":"$0.1003","Low":"$0.08005","Close":"$0.08692","Volume":"$14,772,274","MarketCap":"$0"},{"Date":"Sep 17, 2019","Open":"$0.09052","High":"$0.1003","Low":"$0.08005","Close":"$0.08692","Volume":"$14,772,274","MarketCap":"$0"},{"Date":"Sep 17, 2019","Open":"$0.09052","High":"$0.1003","Low":"$0.08005","Close":"$0.08692","Volume":"$14,772,274","MarketCap":"$0"},{"Date":"Sep 17, 2019","Open":"$0.09052","High":"$0.1003","Low":"$0.08005","Close":"$0.08692","Volume":"$14,772,274","MarketCap":"$0"},{"Date":"Sep 17, 2019","Open":"$0.09052","High":"$0.1003","Low":"$0.08005","Close":"$0.08692","Volume":"$14,772,274","MarketCap":"$0"},{"Date":"Sep 17, 2019","Open":"$0.09052","High":"$0.1003","Low":"$0.08005","Close":"$0.08692","Volume":"$14,772,274","MarketCap":"$0"},{"Date":"Sep 17, 2019","Open":"$0.09052","High":"$0.1003","Low":"$0.08005","Close":"$0.08692","Volume":"$14,772,274","MarketCap":"$0"},{"Date":"Sep 17, 2019","Open":"$0.09052","High":"$0.1003","Low":"$0.08005","Close":"$0.08692","Volume":"$14,772,274","MarketCap":"$0"},{"Date":"Sep 17, 2019","Open":"$0.09052","High":"$0.1003","Low":"$0.08005","Close":"$0.08692","Volume":"$14,772,274","MarketCap":"$0"},{"Date":"Sep 17, 2019","Open":"$0.09052","High":"$0.1003","Low":"$0.08005","Close":"$0.08692","Volume":"$14,772,274","MarketCap":"$0"},{"Date":"Sep 17, 2019","Open":"$0.09052","High":"$0.1003","Low":"$0.08005","Close":"$0.08692","Volume":"$14,772,274","MarketCap":"$0"},{"Date":"Sep 17, 2019","Open":"$0.09052","High":"$0.1003","Low":"$0.08005","Close":"$0.08692","Volume":"$14,772,274","MarketCap":"$0"},{"Date":"Sep 17, 2019","Open":"$0.09052","High":"$0.1003","Low":"$0.08005","Close":"$0.08692","Volume":"$14,772,274","MarketCap":"$0"},{"Date":"Sep 17, 2019","Open":"$0.09052","High":"$0.1003","Low":"$0.08005","Close":"$0.08692","Volume":"$14,772,274","MarketCap":"$0"},{"Date":"Sep 17, 2019","Open":"$0.09052","High":"$0.1003","Low":"$0.08005","Close":"$0.08692","Volume":"$14,772,274","MarketCap":"$0"},{"Date":"Sep 17, 2019","Open":"$0.09052","High":"$0.1003","Low":"$0.08005","Close":"$0.08692","Volume":"$14,772,274","MarketCap":"$0"},{"Date":"Sep 17, 2019","Open":"$0.09052","High":"$0.1003","Low":"$0.08005","Close":"$0.08692","Volume":"$14,772,274","MarketCap":"$0"},{"Date":"Sep 17, 2019","Open":"$0.09052","High":"$0.1003","Low":"$0.08005","Close":"$0.08692","Volume":"$14,772,274","MarketCap":"$0"},{"Date":"Sep 17, 2019","Open":"$0.09052","High":"$0.1003","Low":"$0.08005","Close":"$0.08692","Volume":"$14,772,274","MarketCap":"$0"},{"Date":"Sep 17, 2019","Open":"$0.09052","High":"$0.1003","Low":"$0.08005","Close":"$0.08692","Volume":"$14,772,274","MarketCap":"$0"},{"Date":"Sep 17, 2019","Open":"$0.09052","High":"$0.1003","Low":"$0.08005","Close":"$0.08692","Volume":"$14,772,274","MarketCap":"$0"},{"Date":"Sep 17, 2019","Open":"$0.09052","High":"$0.1003","Low":"$0.08005","Close":"$0.08692","Volume":"$14,772,274","MarketCap":"$0"},{"Date":"Sep 17, 2019","Open":"$0.09052","High":"$0.1003","Low":"$0.08005","Close":"$0.08692","Volume":"$14,772,274","MarketCap":"$0"},{"Date":"Sep 17, 2019","Open":"$0.09052","High":"$0.1003","Low":"$0.08005","Close":"$0.08692","Volume":"$14,772,274","MarketCap":"$0"},{"Date":"Sep 17, 2019","Open":"$0.09052","High":"$0.1003","Low":"$0.08005","Close":"$0.08692","Volume":"$14,772,274","MarketCap":"$0"},{"Date":"Sep 17, 2019","Open":"$0.09052","High":"$0.1003","Low":"$0.08005","Close":"$0.08692","Volume":"$14,772,274","MarketCap":"$0"},{"Date":"Sep 17, 2019","Open":"$0.09052","High":"$0.1003","Low":"$0.08005","Close":"$0.08692","Volume":"$14,772,274","MarketCap":"$0"},{"Date":"Sep 17, 2019","Open":"$0.09052","High":"$0.1003","Low":"$0.08005","Close":"$0.08692","Volume":"$14,772,274","MarketCap":"$0"},{"Date":"Sep 17, 2019","Open":"$0.09052","High":"$0.1003","Low":"$0.08005","Close":"$0.08692","Volume":"$14,772,274","MarketCap":"$0"},{"Date":"Sep 17, 2019","Open":"$0.09052","High":"$0.1003","Low":"$0.08005","Close":"$0.08692","Volume":"$14,772,274","MarketCap":"$0"},{"Date":"Sep 17, 2019","Open":"$0.09052","High":"$0.1003","Low":"$0.08005","Close":"$0.08692","Volume":"$14,772,274","MarketCap":"$0"},{"Date":"Sep 17, 2019","Open":"$0.09052","High":"$0.1003","Low":"$0.08005","Close":"$0.08692","Volume":"$14,772,274","MarketCap":"$0"},{"Date":"Sep 17, 2019","Open":"$0.09052","High":"$0.1003","Low":"$0.08005","Close":"$0.08692","Volume":"$14,772,274","MarketCap":"$0"},{"Date":"Sep 17, 2019","Open":"$0.09052","High":"$0.1003","Low":"$0.08005","Close":"$0.08692","Volume":"$14,772,274","MarketCap":"$0"},{"Date":"Sep 17, 2019","Open":"$0.09052","High":"$0.1003","Low":"$0.08005","Close":"$0.08692","Volume":"$14,772,274","MarketCap":"$0"},{"Date":"Sep 17, 2019","Open":"$0.09052","High":"$0.1003","Low":"$0.08005","Close":"$0.08692","Volume":"$14,772,274","MarketCap":"$0"},{"Date":"Sep 17, 2019","Open":"$0.09052","High":"$0.1003","Low":"$0.08005","Close":"$0.08692","Volume":"$14,772,274","MarketCap":"$0"},{"Date":"Sep 17, 2019","Open":"$0.09052","High":"$0.1003","Low":"$0.08005","Close":"$0.08692","Volume":"$14,772,274","MarketCap":"$0"},{"Date":"Sep 17, 2019","Open":"$0.09052","High":"$0.1003","Low":"$0.08005","Close":"$0.08692","Volume":"$14,772,274","MarketCap":"$0"},{"Date":"Sep 17, 2019","Open":"$0.09052","High":"$0.1003","Low":"$0.08005","Close":"$0.08692","Volume":"$14,772,274","MarketCap":"$0"},{"Date":"Sep 17, 2019","Open":"$0.09052","High":"$0.1003","Low":"$0.08005","Close":"$0.08692","Volume":"$14,772,274","MarketCap":"$0"},{"Date":"Sep 17, 2019","Open":"$0.09052","High":"$0.1003","Low":"$0.08005","Close":"$0.08692","Volume":"$14,772,274","MarketCap":"$0"},{"Date":"Sep 17, 2019","Open":"$0.09052","High":"$0.1003","Low":"$0.08005","Close":"$0.08692","Volume":"$14,772,274","MarketCap":"$0"},{"Date":"Sep 17, 2019","Open":"$0.09052","High":"$0.1003","Low":"$0.08005","Close":"$0.08692","Volume":"$14,772,274","MarketCap":"$0"},{"Date":"Sep 17, 2019","Open":"$0.09052","High":"$0.1003","Low":"$0.08005","Close":"$0.08692","Volume":"$14,772,274","MarketCap":"$0"},{"Date":"Sep 17, 2019","Open":"$0.09052","High":"$0.1003","Low":"$0.08005","Close":"$0.08692","Volume":"$14,772,274","MarketCap":"$0"},{"Date":"Sep 17, 2019","Open":"$0.09052","High":"$0.1003","Low":"$0.08005","Close":"$0.08692","Volume":"$14,772,274","MarketCap":"$0"},{"Date":"Sep 17, 2019","Open":"$0.09052","High":"$0.1003","Low":"$0.08005","Close":"$0.08692","Volume":"$14,772,274","MarketCap":"$0"},{"Date":"Sep 17, 2019","Open":"$0.09052","High":"$0.1003","Low":"$0.08005","Close":"$0.08692","Volume":"$14,772,274","MarketCap":"$0"},{"Date":"Sep 17, 2019","Open":"$0.09052","High":"$0.1003","Low":"$0.08005","Close":"$0.08692","Volume":"$14,772,274","MarketCap":"$0"},{"Date":"Sep 17, 2019","Open":"$0.09052","High":"$0.1003","Low":"$0.08005","Close":"$0.08692","Volume":"$14,772,274","MarketCap":"$0"},{"Date":"Sep 17, 2019","Open":"$0.09052","High":"$0.1003","Low":"$0.08005","Close":"$0.08692","Volume":"$14,772,274","MarketCap":"$0"},{"Date":"Sep 17, 2019","Open":"$0.09052","High":"$0.1003","Low":"$0.08005","Close":"$0.08692","Volume":"$14,772,274","MarketCap":"$0"},{"Date":"Sep 17, 2019","Open":"$0.09052","High":"$0.1003","Low":"$0.08005","Close":"$0.08692","Volume":"$14,772,274","MarketCap":"$0"},{"Date":"Sep 17, 2019","Open":"$0.09052","High":"$0.1003","Low":"$0.08005","Close":"$0.08692","Volume":"$14,772,274","MarketCap":"$0"},{"Date":"Sep 17, 2019","Open":"$0.09052","High":"$0.1003","Low":"$0.08005","Close":"$0.08692","Volume":"$14,772,274","MarketCap":"$0"},{"Date":"Sep 17, 2019","Open":"$0.09052","High":"$0.1003","Low":"$0.08005","Close":"$0.08692","Volume":"$14,772,274","MarketCap":"$0"},{"Date":"Sep 17, 2019","Open":"$0.09052","High":"$0.1003","Low":"$0.08005","Close":"$0.08692","Volume":"$14,772,274","MarketCap":"$0"},{"Date":"Sep 17, 2019","Open":"$0.09052","High":"$0.1003","Low":"$0.08005","Close":"$0.08692","Volume":"$14,772,274","MarketCap":"$0"},{"Date":"Sep 17, 2019","Open":"$0.09052","High":"$0.1003","Low":"$0.08005","Close":"$0.08692","Volume":"$14,772,274","MarketCap":"$0"},{"Date":"Sep 17, 2019","Open":"$0.09052","High":"$0.1003","Low":"$0.08005","Close":"$0.08692","Volume":"$14,772,274","MarketCap":"$0"},{"Date":"Sep 17, 2019","Open":"$0.09052","High":"$0.1003","Low":"$0.08005","Close":"$0.08692","Volume":"$14,772,274","MarketCap":"$0"},{"Date":"Sep 17, 2019","Open":"$0.09052","High":"$0.1003","Low":"$0.08005","Close":"$0.08692","Volume":"$14,772,274","MarketCap":"$0"},{"Date":"Sep 17, 2019","Open":"$0.09052","High":"$0.1003","Low":"$0.08005","Close":"$0.08692","Volume":"$14,772,274","MarketCap":"$0"},{"Date":"Sep 17, 2019","Open":"$0.09052","High":"$0.1003","Low":"$0.08005","Close":"$0.08692","Volume":"$14,772,274","MarketCap":"$0"},{"Date":"Sep 17, 2019","Open":"$0.09052","High":"$0.1003","Low":"$0.08005","Close":"$0.08692","Volume":"$14,772,274","MarketCap":"$0"},{"Date":"Sep 17, 2019","Open":"$0.09052","High":"$0.1003","Low":"$0.08005","Close":"$0.08692","Volume":"$14,772,274","MarketCap":"$0"},{"Date":"Sep 17, 2019","Open":"$0.09052","High":"$0.1003","Low":"$0.08005","Close":"$0.08692","Volume":"$14,772,274","MarketCap":"$0"},{"Date":"Sep 17, 2019","Open":"$0.09052","High":"$0.1003","Low":"$0.08005","Close":"$0.08692","Volume":"$14,772,274","MarketCap":"$0"},{"Date":"Sep 17, 2019","Open":"$0.09052","High":"$0.1003","Low":"$0.08005","Close":"$0.08692","Volume":"$14,772,274","MarketCap":"$0"},{"Date":"Sep 17, 2019","Open":"$0.09052","High":"$0.1003","Low":"$0.08005","Close":"$0.08692","Volume":"$14,772,274","MarketCap":"$0"},{"Date":"Sep 17, 2019","Open":"$0.09052","High":"$0.1003","Low":"$0.08005","Close":"$0.08692","Volume":"$14,772,274","MarketCap":"$0"},{"Date":"Sep 17, 2019","Open":"$0.09052","High":"$0.1003","Low":"$0.08005","Close":"$0.08692","Volume":"$14,772,274","MarketCap":"$0"},{"Date":"Sep 17, 2019","Open":"$0.09052","High":"$0.1003","Low":"$0.08005","Close":"$0.08692","Volume":"$14,772,274","MarketCap":"$0"},{"Date":"Sep 17, 2019","Open":"$0.09052","High":"$0.1003","Low":"$0.08005","Close":"$0.08692","Volume":"$14,772,274","MarketCap":"$0"},{"Date":"Sep 17, 2019","Open":"$0.09052","High":"$0.1003","Low":"$0.08005","Close":"$0.08692","Volume":"$14,772,274","MarketCap":"$0"},{"Date":"Sep 17, 2019","Open":"$0.09052","High":"$0.1003","Low":"$0.08005","Close":"$0.08692","Volume":"$14,772,274","MarketCap":"$0"},{"Date":"Sep 17, 2019","Open":"$0.09052","High":"$0.1003","Low":"$0.08005","Close":"$0.08692","Volume":"$14,772,274","MarketCap":"$0"},{"Date":"Sep 17, 2019","Open":"$0.09052","High":"$0.1003","Low":"$0.08005","Close":"$0.08692","Volume":"$14,772,274","MarketCap":"$0"},{"Date":"Sep 17, 2019","Open":"$0.09052","High":"$0.1003","Low":"$0.08005","Close":"$0.08692","Volume":"$14,772,274","MarketCap":"$0"},{"Date":"Sep 17, 2019","Open":"$0.09052","High":"$0.1003","Low":"$0.08005","Close":"$0.08692","Volume":"$14,772,274","MarketCap":"$0"},{"Date":"Sep 17, 2019","Open":"$0.09052","High":"$0.1003","Low":"$0.08005","Close":"$0.08692","Volume":"$14,772,274","MarketCap":"$0"},{"Date":"Sep 17, 2019","Open":"$0.09052","High":"$0.1003","Low":"$0.08005","Close":"$0.08692","Volume":"$14,772,274","MarketCap":"$0"},{"Date":"Sep 17, 2019","Open":"$0.09052","High":"$0.1003","Low":"$0.08005","Close":"$0.08692","Volume":"$14,772,274","MarketCap":"$0"},{"Date":"Sep 17, 2019","Open":"$0.09052","High":"$0.1003","Low":"$0.08005","Close":"$0.08692","Volume":"$14,772,274","MarketCap":"$0"},{"Date":"Sep 17, 2019","Open":"$0.09052","High":"$0.1003","Low":"$0.08005","Close":"$0.08692","Volume":"$14,772,274","MarketCap":"$0"},{"Date":"Sep 17, 2019","Open":"$0.09052","High":"$0.1003","Low":"$0.08005","Close":"$0.08692","Volume":"$14,772,274","MarketCap":"$0"},{"Date":"Sep 17, 2019","Open":"$0.09052","High":"$0.1003","Low":"$0.08005","Close":"$0.08692","Volume":"$14,772,274","MarketCap":"$0"},{"Date":"Sep 17, 2019","Open":"$0.09052","High":"$0.1003","Low":"$0.08005","Close":"$0.08692","Volume":"$14,772,274","MarketCap":"$0"},{"Date":"Sep 17, 2019","Open":"$0.09052","High":"$0.1003","Low":"$0.08005","Close":"$0.08692","Volume":"$14,772,274","MarketCap":"$0"}]